[
    {
        "fit": [
            29.409714285714283, 
            0.10770650801966995
        ]
    }, 
    {
        "fit": [
            27.56985714285714, 
            0.10816909706713602
        ]
    }, 
    {
        "fit": [
            23.517428571428574, 
            0.11085073669360003
        ]
    }, 
    {
        "fit": [
            20.411, 
            0.11561876891648001
        ]
    }, 
    {
        "fit": [
            19.403285714285715, 
            0.11780247780799999
        ]
    }, 
    {
        "fit": [
            19.295428571428573, 
            0.12287384640000001
        ]
    }, 
    {
        "fit": [
            18.473000000000003, 
            0.128068852427917
        ]
    }, 
    {
        "fit": [
            17.60871428571429, 
            0.13983237532685713
        ]
    }, 
    {
        "fit": [
            16.723142857142857, 
            0.14331212177542854
        ]
    }, 
    {
        "fit": [
            15.728142857142858, 
            0.14488537969205026
        ]
    }, 
    {
        "fit": [
            15.566714285714284, 
            0.14897981570119315
        ]
    }, 
    {
        "fit": [
            15.073857142857142, 
            0.1513362280026514
        ]
    }, 
    {
        "fit": [
            14.778714285714285, 
            0.15393785667108575
        ]
    }, 
    {
        "fit": [
            14.739285714285716, 
            0.1605146977443365
        ]
    }, 
    {
        "fit": [
            14.065857142857144, 
            0.16593829674613872
        ]
    }, 
    {
        "fit": [
            13.541142857142859, 
            0.1954993465889128
        ]
    }
]