[
    {
        "fit": [
            437.92857142857144, 
            0.2532772572870218
        ]
    }, 
    {
        "fit": [
            436.57142857142856, 
            0.2533023297895659
        ]
    }, 
    {
        "fit": [
            435.5, 
            0.25387952697542887
        ]
    }, 
    {
        "fit": [
            434.07142857142856, 
            0.25521433658964027
        ]
    }, 
    {
        "fit": [
            418.92857142857144, 
            0.2555227123575712
        ]
    }, 
    {
        "fit": [
            418.42857142857144, 
            0.25616009578585636
        ]
    }, 
    {
        "fit": [
            399.35714285714283, 
            0.257536885984516
        ]
    }, 
    {
        "fit": [
            393.14285714285717, 
            0.2765689729006204
        ]
    }, 
    {
        "fit": [
            364.2857142857143, 
            0.2910549971710471
        ]
    }, 
    {
        "fit": [
            323.85714285714283, 
            0.323588276148665
        ]
    }, 
    {
        "fit": [
            318.2857142857143, 
            0.3390649280136556
        ]
    }, 
    {
        "fit": [
            311.07142857142856, 
            0.33945147397591147
        ]
    }, 
    {
        "fit": [
            305.85714285714283, 
            0.34042371798899096
        ]
    }, 
    {
        "fit": [
            302.2142857142857, 
            0.34537890855992615
        ]
    }, 
    {
        "fit": [
            295.57142857142856, 
            0.34604931181129045
        ]
    }, 
    {
        "fit": [
            295.42857142857144, 
            0.3582667100796425
        ]
    }, 
    {
        "fit": [
            284.42857142857144, 
            0.35829022298531304
        ]
    }, 
    {
        "fit": [
            280.35714285714283, 
            0.36451769918585963
        ]
    }, 
    {
        "fit": [
            279.2857142857143, 
            0.37268421028871984
        ]
    }, 
    {
        "fit": [
            278.42857142857144, 
            0.374496843694139
        ]
    }, 
    {
        "fit": [
            278.2142857142857, 
            0.3813727802059664
        ]
    }, 
    {
        "fit": [
            278.14285714285717, 
            0.3826912120841376
        ]
    }, 
    {
        "fit": [
            278.0, 
            0.3832838252734316
        ]
    }
]