[
    {
        "fit": [
            21.727071428571428, 
            0.10594782421389741
        ]
    }, 
    {
        "fit": [
            19.077928571428572, 
            0.11005715644818682
        ]
    }, 
    {
        "fit": [
            17.947571428571433, 
            0.11363891987589263
        ]
    }, 
    {
        "fit": [
            17.711928571428572, 
            0.12232439151087501
        ]
    }, 
    {
        "fit": [
            17.46, 
            0.12739625732532958
        ]
    }, 
    {
        "fit": [
            16.934285714285714, 
            0.1280611191755291
        ]
    }, 
    {
        "fit": [
            16.2875, 
            0.13621192667668977
        ]
    }, 
    {
        "fit": [
            15.42007142857143, 
            0.14025524452662647
        ]
    }, 
    {
        "fit": [
            13.594285714285718, 
            0.14968335202280766
        ]
    }, 
    {
        "fit": [
            13.591000000000003, 
            0.15480705472972453
        ]
    }, 
    {
        "fit": [
            13.357571428571429, 
            0.16812301713598532
        ]
    }, 
    {
        "fit": [
            12.385642857142859, 
            0.17939596133136626
        ]
    }, 
    {
        "fit": [
            12.093571428571432, 
            0.18274901402894125
        ]
    }, 
    {
        "fit": [
            11.200714285714286, 
            0.19251965778990382
        ]
    }, 
    {
        "fit": [
            10.91664285714286, 
            0.19741906012782642
        ]
    }, 
    {
        "fit": [
            10.839142857142859, 
            0.22337858089544474
        ]
    }
]