[
    {
        "fit": [
            22.011, 
            0.09073323253983928
        ]
    }, 
    {
        "fit": [
            21.762, 
            0.09529493488221269
        ]
    }, 
    {
        "fit": [
            18.745166666666666, 
            0.09640214826096098
        ]
    }, 
    {
        "fit": [
            17.532499999999995, 
            0.10136921585463339
        ]
    }, 
    {
        "fit": [
            17.5075, 
            0.10457586437058336
        ]
    }, 
    {
        "fit": [
            15.988666666666662, 
            0.10846974007540365
        ]
    }, 
    {
        "fit": [
            14.833666666666666, 
            0.11021674501463335
        ]
    }, 
    {
        "fit": [
            13.836833333333331, 
            0.11291848794870156
        ]
    }, 
    {
        "fit": [
            11.682333333333332, 
            0.11669684340725338
        ]
    }, 
    {
        "fit": [
            11.628833333333333, 
            0.1171427126190634
        ]
    }, 
    {
        "fit": [
            11.524666666666667, 
            0.12583976009208336
        ]
    }, 
    {
        "fit": [
            11.452499999999999, 
            0.1275521547523967
        ]
    }
]