[
    {
        "fit": [
            25.53916666666667, 
            0.08920271682903347
        ]
    }, 
    {
        "fit": [
            22.011, 
            0.09073323253983928
        ]
    }, 
    {
        "fit": [
            18.994166666666665, 
            0.09184044591858757
        ]
    }, 
    {
        "fit": [
            18.0055, 
            0.09544299557309303
        ]
    }, 
    {
        "fit": [
            17.5075, 
            0.10457586437058336
        ]
    }, 
    {
        "fit": [
            16.24233333333333, 
            0.10731482121162496
        ]
    }, 
    {
        "fit": [
            15.524833333333332, 
            0.10787562964253168
        ]
    }, 
    {
        "fit": [
            14.856666666666664, 
            0.11233533844870158
        ]
    }, 
    {
        "fit": [
            14.427666666666665, 
            0.11236151064753337
        ]
    }, 
    {
        "fit": [
            13.474333333333332, 
            0.11269734211536821
        ]
    }, 
    {
        "fit": [
            13.0345, 
            0.11473447576325341
        ]
    }, 
    {
        "fit": [
            12.816333333333333, 
            0.116721408727335
        ]
    }, 
    {
        "fit": [
            12.264499999999998, 
            0.1168485545119534
        ]
    }, 
    {
        "fit": [
            11.628833333333333, 
            0.1171427126190634
        ]
    }, 
    {
        "fit": [
            11.190666666666665, 
            0.12080181891906337
        ]
    }
]