[
    {
        "fit": [
            32.33072727272727, 
            0.12869745852076897
        ]
    }, 
    {
        "fit": [
            30.938, 
            0.13268507856666292
        ]
    }, 
    {
        "fit": [
            27.200363636363637, 
            0.1394046055277222
        ]
    }, 
    {
        "fit": [
            23.650772727272734, 
            0.13971284211500115
        ]
    }, 
    {
        "fit": [
            23.64013636363637, 
            0.13998923302903832
        ]
    }, 
    {
        "fit": [
            23.071727272727276, 
            0.14541453149457662
        ]
    }, 
    {
        "fit": [
            20.573181818181816, 
            0.15407634417757538
        ]
    }, 
    {
        "fit": [
            20.147181818181817, 
            0.1649979447106971
        ]
    }, 
    {
        "fit": [
            19.423636363636366, 
            0.1812844552687076
        ]
    }, 
    {
        "fit": [
            15.330272727272728, 
            0.18712862761269233
        ]
    }, 
    {
        "fit": [
            14.036863636363636, 
            0.2089294364623688
        ]
    }, 
    {
        "fit": [
            14.028863636363633, 
            0.23570330411475063
        ]
    }, 
    {
        "fit": [
            13.86618181818182, 
            0.23707318852323428
        ]
    }, 
    {
        "fit": [
            13.75081818181818, 
            0.23727326130703263
        ]
    }, 
    {
        "fit": [
            13.626363636363635, 
            0.2514831534450442
        ]
    }, 
    {
        "fit": [
            13.523499999999997, 
            0.2537715771699468
        ]
    }
]