[
    {
        "fit": [
            23.42566666666666, 
            0.14125625113958382
        ]
    }, 
    {
        "fit": [
            22.642166666666665, 
            0.1450728105899083
        ]
    }, 
    {
        "fit": [
            21.763666666666666, 
            0.14782815336965832
        ]
    }, 
    {
        "fit": [
            20.780333333333335, 
            0.1695848772639795
        ]
    }, 
    {
        "fit": [
            19.46816666666667, 
            0.1761837280476404
        ]
    }, 
    {
        "fit": [
            17.410833333333333, 
            0.19800480128086942
        ]
    }, 
    {
        "fit": [
            16.98266666666667, 
            0.2033865081685351
        ]
    }, 
    {
        "fit": [
            16.679666666666666, 
            0.21253081193086945
        ]
    }, 
    {
        "fit": [
            16.63733333333333, 
            0.2180623872566295
        ]
    }, 
    {
        "fit": [
            16.1555, 
            0.22365371111467294
        ]
    }, 
    {
        "fit": [
            15.382, 
            0.24371129709043302
        ]
    }, 
    {
        "fit": [
            15.291333333333334, 
            0.2543922965116278
        ]
    }
]