[
    {
        "fit": [
            26.979999999999997, 
            0.131741289247523
        ]
    }, 
    {
        "fit": [
            24.2883, 
            0.13304327394929355
        ]
    }, 
    {
        "fit": [
            22.2353, 
            0.13505309304267427
        ]
    }, 
    {
        "fit": [
            17.4271, 
            0.1392883060993836
        ]
    }, 
    {
        "fit": [
            15.851000000000003, 
            0.1415217449488158
        ]
    }, 
    {
        "fit": [
            13.945500000000001, 
            0.15281414774222402
        ]
    }, 
    {
        "fit": [
            13.751499999999998, 
            0.16186984391566264
        ]
    }, 
    {
        "fit": [
            12.2683, 
            0.16506774724720966
        ]
    }, 
    {
        "fit": [
            12.231399999999999, 
            0.18398631084538167
        ]
    }, 
    {
        "fit": [
            11.786299999999999, 
            0.1888855661872876
        ]
    }, 
    {
        "fit": [
            11.0925, 
            0.2033933794745298
        ]
    }, 
    {
        "fit": [
            10.569999999999999, 
            0.22237272725640628
        ]
    }
]