[
    {
        "fit": [
            24.9962, 
            0.1291192575007339
        ]
    }, 
    {
        "fit": [
            24.323, 
            0.13173231476281871
        ]
    }, 
    {
        "fit": [
            19.565199999999997, 
            0.13306557635118366
        ]
    }, 
    {
        "fit": [
            17.9492, 
            0.14604972762427018
        ]
    }, 
    {
        "fit": [
            15.999799999999999, 
            0.14806783536912738
        ]
    }, 
    {
        "fit": [
            14.6053, 
            0.15271406278639996
        ]
    }, 
    {
        "fit": [
            14.1042, 
            0.1570159913810946
        ]
    }, 
    {
        "fit": [
            13.249, 
            0.15791001184368003
        ]
    }, 
    {
        "fit": [
            12.3567, 
            0.16154735919511137
        ]
    }, 
    {
        "fit": [
            10.5221, 
            0.16315512017203676
        ]
    }
]