[
    {
        "fit": [
            22.845249999999997, 
            0.12619699011083904
        ]
    }, 
    {
        "fit": [
            21.237916666666667, 
            0.12667797687643984
        ]
    }, 
    {
        "fit": [
            20.142083333333332, 
            0.126736303344474
        ]
    }, 
    {
        "fit": [
            19.747583333333335, 
            0.13545803569615436
        ]
    }, 
    {
        "fit": [
            19.741500000000002, 
            0.13813255758116055
        ]
    }, 
    {
        "fit": [
            19.6555, 
            0.13948857180383603
        ]
    }, 
    {
        "fit": [
            19.49275, 
            0.13980311043611024
        ]
    }, 
    {
        "fit": [
            18.986916666666666, 
            0.1401703827239044
        ]
    }, 
    {
        "fit": [
            18.746166666666667, 
            0.14804368631748546
        ]
    }, 
    {
        "fit": [
            18.600166666666667, 
            0.15167980594164143
        ]
    }, 
    {
        "fit": [
            18.577333333333332, 
            0.1528065540711846
        ]
    }, 
    {
        "fit": [
            17.425249999999995, 
            0.15339088084952276
        ]
    }, 
    {
        "fit": [
            17.394666666666666, 
            0.15535427990672748
        ]
    }, 
    {
        "fit": [
            17.193166666666666, 
            0.16099631325067407
        ]
    }, 
    {
        "fit": [
            17.1775, 
            0.16349541282152405
        ]
    }, 
    {
        "fit": [
            17.100749999999998, 
            0.16384394157619395
        ]
    }, 
    {
        "fit": [
            17.062916666666666, 
            0.16647024126817864
        ]
    }, 
    {
        "fit": [
            16.337166666666665, 
            0.1678059314604979
        ]
    }, 
    {
        "fit": [
            16.189249999999998, 
            0.16924447477659374
        ]
    }, 
    {
        "fit": [
            16.135749999999998, 
            0.1743698740394284
        ]
    }, 
    {
        "fit": [
            16.096499999999995, 
            0.17558383521439638
        ]
    }, 
    {
        "fit": [
            15.930999999999997, 
            0.1762628589096552
        ]
    }, 
    {
        "fit": [
            15.90225, 
            0.18056296792356308
        ]
    }, 
    {
        "fit": [
            15.823166666666665, 
            0.18442156598356305
        ]
    }, 
    {
        "fit": [
            15.792249999999996, 
            0.20278831245950524
        ]
    }
]