[
    {
        "fit": [
            355.7, 
            0.12031757445716025
        ]
    }, 
    {
        "fit": [
            351.9, 
            0.12038142446767863
        ]
    }, 
    {
        "fit": [
            332.5, 
            0.1208724246828228
        ]
    }, 
    {
        "fit": [
            329.9, 
            0.12223182468282281
        ]
    }, 
    {
        "fit": [
            328.1, 
            0.12535598270162038
        ]
    }, 
    {
        "fit": [
            325.4, 
            0.12696057794847704
        ]
    }, 
    {
        "fit": [
            324.5, 
            0.12916826723270683
        ]
    }, 
    {
        "fit": [
            322.2, 
            0.13072504187887352
        ]
    }, 
    {
        "fit": [
            204.6, 
            0.13337129750470206
        ]
    }, 
    {
        "fit": [
            186.8, 
            0.1345977367068355
        ]
    }, 
    {
        "fit": [
            180.4, 
            0.13601947927173313
        ]
    }, 
    {
        "fit": [
            178.4, 
            0.1368493329796223
        ]
    }, 
    {
        "fit": [
            174.6, 
            0.13691167554451994
        ]
    }, 
    {
        "fit": [
            170.4, 
            0.1379485836936168
        ]
    }, 
    {
        "fit": [
            168.6, 
            0.14014526404514768
        ]
    }, 
    {
        "fit": [
            168.1, 
            0.14495546596292364
        ]
    }, 
    {
        "fit": [
            165.4, 
            0.14748466514842468
        ]
    }, 
    {
        "fit": [
            162.2, 
            0.15019776612042837
        ]
    }, 
    {
        "fit": [
            159.1, 
            0.1516861640380905
        ]
    }, 
    {
        "fit": [
            156.2, 
            0.15255879892775637
        ]
    }, 
    {
        "fit": [
            147.3, 
            0.15466103728370875
        ]
    }, 
    {
        "fit": [
            146.6, 
            0.15863232673010874
        ]
    }, 
    {
        "fit": [
            146.5, 
            0.16057164066478075
        ]
    }, 
    {
        "fit": [
            146.4, 
            0.16467118980528456
        ]
    }, 
    {
        "fit": [
            145.3, 
            0.16821061420370872
        ]
    }, 
    {
        "fit": [
            141.3, 
            0.17062289688926136
        ]
    }, 
    {
        "fit": [
            140.5, 
            0.17653350027033338
        ]
    }, 
    {
        "fit": [
            137.8, 
            0.18212651832580679
        ]
    }, 
    {
        "fit": [
            130.9, 
            0.18260702807268575
        ]
    }, 
    {
        "fit": [
            128.7, 
            0.18875074582002527
        ]
    }, 
    {
        "fit": [
            128.0, 
            0.1927220352664253
        ]
    }, 
    {
        "fit": [
            127.9, 
            0.1946613492010973
        ]
    }, 
    {
        "fit": [
            127.3, 
            0.20029013952648927
        ]
    }, 
    {
        "fit": [
            126.7, 
            0.2023003227400253
        ]
    }, 
    {
        "fit": [
            126.6, 
            0.2042614289728893
        ]
    }, 
    {
        "fit": [
            126.5, 
            0.20620074290756127
        ]
    }, 
    {
        "fit": [
            125.9, 
            0.2082109261210973
        ]
    }, 
    {
        "fit": [
            125.8, 
            0.21017203235396126
        ]
    }, 
    {
        "fit": [
            125.3, 
            0.21383971644648928
        ]
    }, 
    {
        "fit": [
            124.5, 
            0.21975031982756127
        ]
    }
]