[
    {
        "fit": [
            17.019142857142857, 
            0.06686395022986531
        ]
    }, 
    {
        "fit": [
            15.997, 
            0.06736751883246864
        ]
    }, 
    {
        "fit": [
            15.624285714285714, 
            0.07335966531771433
        ]
    }, 
    {
        "fit": [
            15.429142857142855, 
            0.07659046875843675
        ]
    }, 
    {
        "fit": [
            14.407, 
            0.07709403736104008
        ]
    }, 
    {
        "fit": [
            14.034285714285714, 
            0.08308618384628577
        ]
    }, 
    {
        "fit": [
            13.971285714285715, 
            0.08716868132618295
        ]
    }, 
    {
        "fit": [
            13.543857142857144, 
            0.09028005593965951
        ]
    }, 
    {
        "fit": [
            13.41285714285714, 
            0.09275083434082532
        ]
    }, 
    {
        "fit": [
            12.390714285714283, 
            0.09325440294342865
        ]
    }, 
    {
        "fit": [
            12.251999999999997, 
            0.10763505659628579
        ]
    }, 
    {
        "fit": [
            11.825857142857142, 
            0.10911142735257152
        ]
    }, 
    {
        "fit": [
            11.721571428571426, 
            0.11288910086532915
        ]
    }, 
    {
        "fit": [
            11.653571428571427, 
            0.1166645303202761
        ]
    }, 
    {
        "fit": [
            11.597714285714286, 
            0.11704956338591553
        ]
    }, 
    {
        "fit": [
            11.565, 
            0.1197296371793738
        ]
    }, 
    {
        "fit": [
            11.405285714285712, 
            0.12203580687457152
        ]
    }, 
    {
        "fit": [
            11.105857142857143, 
            0.12244760788828578
        ]
    }, 
    {
        "fit": [
            10.949857142857143, 
            0.12423501301941893
        ]
    }, 
    {
        "fit": [
            10.633285714285714, 
            0.13718159732047203
        ]
    }, 
    {
        "fit": [
            10.566714285714285, 
            0.1490892136033292
        ]
    }, 
    {
        "fit": [
            10.43757142857143, 
            0.15487159404732917
        ]
    }, 
    {
        "fit": [
            10.236, 
            0.17257025468636586
        ]
    }, 
    {
        "fit": [
            9.88342857142857, 
            0.17925836830721328
        ]
    }, 
    {
        "fit": [
            9.065142857142858, 
            0.1890443735414574
        ]
    }
]