[
    {
        "fit": [
            29.97568181818181, 
            0.12972377347173367
        ]
    }, 
    {
        "fit": [
            28.70768181818181, 
            0.13337289879742614
        ]
    }, 
    {
        "fit": [
            25.99568181818181, 
            0.13747117771060638
        ]
    }, 
    {
        "fit": [
            24.45040909090909, 
            0.13895453542662559
        ]
    }, 
    {
        "fit": [
            20.886227272727275, 
            0.14055822688617892
        ]
    }, 
    {
        "fit": [
            19.66727272727272, 
            0.14661656544924312
        ]
    }, 
    {
        "fit": [
            15.585636363636365, 
            0.192012620251832
        ]
    }, 
    {
        "fit": [
            15.490227272727276, 
            0.20982871102474088
        ]
    }, 
    {
        "fit": [
            15.34481818181818, 
            0.21026687796028753
        ]
    }, 
    {
        "fit": [
            14.897136363636365, 
            0.21483365878576022
        ]
    }, 
    {
        "fit": [
            13.031045454545454, 
            0.21625977564045726
        ]
    }, 
    {
        "fit": [
            12.52972727272727, 
            0.21916115025533903
        ]
    }
]