[
    {
        "fit": [
            27.02590909090909, 
            0.12767239185741847
        ]
    }, 
    {
        "fit": [
            24.858727272727275, 
            0.13424232116945597
        ]
    }, 
    {
        "fit": [
            24.04709090909091, 
            0.13905430331735175
        ]
    }, 
    {
        "fit": [
            23.57981818181818, 
            0.147410188078357
        ]
    }, 
    {
        "fit": [
            22.07168181818182, 
            0.15048909250602419
        ]
    }, 
    {
        "fit": [
            19.840818181818182, 
            0.15887118022158092
        ]
    }, 
    {
        "fit": [
            19.54495454545454, 
            0.15994880112055615
        ]
    }, 
    {
        "fit": [
            18.744999999999997, 
            0.16339615693976398
        ]
    }, 
    {
        "fit": [
            18.672863636363637, 
            0.16718670823981133
        ]
    }, 
    {
        "fit": [
            18.10022727272727, 
            0.16766487507365346
        ]
    }, 
    {
        "fit": [
            17.804818181818185, 
            0.1704389823137256
        ]
    }, 
    {
        "fit": [
            17.65381818181818, 
            0.1803423472690122
        ]
    }, 
    {
        "fit": [
            15.841772727272724, 
            0.18079128685332238
        ]
    }, 
    {
        "fit": [
            11.926681818181818, 
            0.21567658780579094
        ]
    }, 
    {
        "fit": [
            10.851136363636364, 
            0.21732284368475563
        ]
    }, 
    {
        "fit": [
            10.448636363636364, 
            0.2246687349186641
        ]
    }, 
    {
        "fit": [
            10.41990909090909, 
            0.235577494928813
        ]
    }, 
    {
        "fit": [
            10.26018181818182, 
            0.24569174834296803
        ]
    }
]