[
    {
        "fit": [
            32.663909090909094, 
            0.12892041654784733
        ]
    }, 
    {
        "fit": [
            32.3045, 
            0.13307389398982272
        ]
    }, 
    {
        "fit": [
            30.32422727272727, 
            0.13450334589616492
        ]
    }, 
    {
        "fit": [
            27.77390909090909, 
            0.13521336201103565
        ]
    }, 
    {
        "fit": [
            27.308500000000002, 
            0.1391235073676994
        ]
    }, 
    {
        "fit": [
            24.79577272727273, 
            0.1398250314433997
        ]
    }, 
    {
        "fit": [
            24.674227272727272, 
            0.1452215598816392
        ]
    }, 
    {
        "fit": [
            24.40213636363637, 
            0.14712384192905564
        ]
    }, 
    {
        "fit": [
            23.306272727272724, 
            0.14872333606431506
        ]
    }, 
    {
        "fit": [
            22.941636363636363, 
            0.1601298434417977
        ]
    }, 
    {
        "fit": [
            21.14272727272727, 
            0.16050280128871316
        ]
    }, 
    {
        "fit": [
            20.459454545454545, 
            0.1632070721248147
        ]
    }, 
    {
        "fit": [
            18.944954545454546, 
            0.16455275646737885
        ]
    }, 
    {
        "fit": [
            15.035681818181821, 
            0.16495517319870737
        ]
    }, 
    {
        "fit": [
            12.27177272727273, 
            0.20894170174113944
        ]
    }, 
    {
        "fit": [
            10.39436363636364, 
            0.209693266884073
        ]
    }, 
    {
        "fit": [
            9.712227272727274, 
            0.2168719503005816
        ]
    }
]