[
    {
        "fit": [
            29.500272727272726, 
            0.12642350930810348
        ]
    }, 
    {
        "fit": [
            27.17581818181818, 
            0.13329576444166938
        ]
    }, 
    {
        "fit": [
            26.551909090909092, 
            0.13718618736478705
        ]
    }, 
    {
        "fit": [
            22.541954545454548, 
            0.13762846716446012
        ]
    }, 
    {
        "fit": [
            20.255954545454546, 
            0.14880007441296172
        ]
    }, 
    {
        "fit": [
            19.838090909090912, 
            0.16210245251130412
        ]
    }, 
    {
        "fit": [
            19.542545454545454, 
            0.17239988939458764
        ]
    }, 
    {
        "fit": [
            18.97863636363636, 
            0.18364979356444994
        ]
    }, 
    {
        "fit": [
            17.816772727272724, 
            0.18887606777315769
        ]
    }, 
    {
        "fit": [
            11.563954545454544, 
            0.21561457448840973
        ]
    }, 
    {
        "fit": [
            10.808499999999997, 
            0.2182217462124435
        ]
    }, 
    {
        "fit": [
            10.101909090909091, 
            0.22067331756857567
        ]
    }, 
    {
        "fit": [
            9.607045454545455, 
            0.23461226825319537
        ]
    }, 
    {
        "fit": [
            9.357000000000001, 
            0.23901120306609755
        ]
    }
]