[
    {
        "fit": [
            30.443909090909095, 
            0.12658417104987765
        ]
    }, 
    {
        "fit": [
            27.523954545454547, 
            0.1306042038945636
        ]
    }, 
    {
        "fit": [
            27.464136363636364, 
            0.14176919698628793
        ]
    }, 
    {
        "fit": [
            26.454000000000008, 
            0.1420605860825498
        ]
    }, 
    {
        "fit": [
            25.847954545454545, 
            0.143141442665646
        ]
    }, 
    {
        "fit": [
            24.901636363636364, 
            0.14417974096339117
        ]
    }, 
    {
        "fit": [
            24.71995454545455, 
            0.14535796749248808
        ]
    }, 
    {
        "fit": [
            23.41786363636364, 
            0.14881966968416666
        ]
    }, 
    {
        "fit": [
            20.149681818181815, 
            0.1558238918941638
        ]
    }, 
    {
        "fit": [
            18.43736363636364, 
            0.167598599314825
        ]
    }, 
    {
        "fit": [
            17.520909090909093, 
            0.17362772960838296
        ]
    }, 
    {
        "fit": [
            16.128090909090908, 
            0.17842846041245905
        ]
    }, 
    {
        "fit": [
            15.984772727272729, 
            0.20428520389231705
        ]
    }, 
    {
        "fit": [
            10.867454545454548, 
            0.216567621721143
        ]
    }, 
    {
        "fit": [
            10.858818181818181, 
            0.22204545351892221
        ]
    }, 
    {
        "fit": [
            10.358500000000003, 
            0.223334026150353
        ]
    }, 
    {
        "fit": [
            10.176727272727275, 
            0.23861194453293086
        ]
    }
]