[
    {
        "fit": [
            24.560928571428573, 
            0.09727577085136686
        ]
    }, 
    {
        "fit": [
            22.475285714285715, 
            0.09932425131679941
        ]
    }, 
    {
        "fit": [
            22.241714285714288, 
            0.09998520528519052
        ]
    }, 
    {
        "fit": [
            20.86492857142857, 
            0.10179777214231667
        ]
    }, 
    {
        "fit": [
            19.458857142857145, 
            0.11302369248200263
        ]
    }, 
    {
        "fit": [
            19.00971428571429, 
            0.11503897421053975
        ]
    }, 
    {
        "fit": [
            18.292857142857144, 
            0.11673655143025995
        ]
    }, 
    {
        "fit": [
            18.235785714285715, 
            0.12402419147659446
        ]
    }, 
    {
        "fit": [
            18.020928571428573, 
            0.12416977425634636
        ]
    }, 
    {
        "fit": [
            16.506428571428568, 
            0.1269846830214935
        ]
    }, 
    {
        "fit": [
            15.176142857142855, 
            0.12804560808177187
        ]
    }, 
    {
        "fit": [
            12.178142857142857, 
            0.14464989468377057
        ]
    }, 
    {
        "fit": [
            11.99964285714286, 
            0.14600902792481624
        ]
    }, 
    {
        "fit": [
            11.559428571428572, 
            0.18025351330433242
        ]
    }, 
    {
        "fit": [
            11.25564285714286, 
            0.18083425998163882
        ]
    }, 
    {
        "fit": [
            10.838142857142858, 
            0.19221007462439393
        ]
    }, 
    {
        "fit": [
            10.836285714285713, 
            0.22456227537515977
        ]
    }, 
    {
        "fit": [
            10.699857142857143, 
            0.23064990174317604
        ]
    }, 
    {
        "fit": [
            10.668642857142858, 
            0.23071001700785312
        ]
    }, 
    {
        "fit": [
            10.438785714285714, 
            0.24206861488235143
        ]
    }, 
    {
        "fit": [
            10.41214285714286, 
            0.26287821268861994
        ]
    }, 
    {
        "fit": [
            10.299357142857142, 
            0.2774764271112807
        ]
    }, 
    {
        "fit": [
            10.275571428571428, 
            0.31140725665838487
        ]
    }
]