[
    {
        "fit": [
            28.586357142857146, 
            0.09800605748015369
        ]
    }, 
    {
        "fit": [
            20.298642857142855, 
            0.10138593793212934
        ]
    }, 
    {
        "fit": [
            19.639, 
            0.1095038779932905
        ]
    }, 
    {
        "fit": [
            18.975142857142856, 
            0.109711233269255
        ]
    }, 
    {
        "fit": [
            18.419642857142858, 
            0.11018504794630782
        ]
    }, 
    {
        "fit": [
            17.65857142857143, 
            0.1151171160285974
        ]
    }, 
    {
        "fit": [
            16.096857142857143, 
            0.11570444587230384
        ]
    }, 
    {
        "fit": [
            15.315500000000002, 
            0.11988162117309563
        ]
    }, 
    {
        "fit": [
            15.02821428571429, 
            0.1265217713568635
        ]
    }, 
    {
        "fit": [
            14.4725, 
            0.12945269050882666
        ]
    }, 
    {
        "fit": [
            14.353, 
            0.1307634438132302
        ]
    }, 
    {
        "fit": [
            14.175928571428571, 
            0.13241035958556088
        ]
    }, 
    {
        "fit": [
            14.065428571428571, 
            0.13794780975470258
        ]
    }, 
    {
        "fit": [
            13.81307142857143, 
            0.13873025575545397
        ]
    }, 
    {
        "fit": [
            12.40814285714286, 
            0.14428671065106213
        ]
    }, 
    {
        "fit": [
            12.374285714285717, 
            0.14762969497447528
        ]
    }, 
    {
        "fit": [
            11.566142857142859, 
            0.16402196555429807
        ]
    }, 
    {
        "fit": [
            11.558428571428573, 
            0.18361934562568896
        ]
    }, 
    {
        "fit": [
            11.218642857142855, 
            0.18877367625807182
        ]
    }, 
    {
        "fit": [
            10.769428571428573, 
            0.19792348220824696
        ]
    }, 
    {
        "fit": [
            10.580714285714285, 
            0.21852707897871237
        ]
    }, 
    {
        "fit": [
            10.438642857142856, 
            0.28682635397272366
        ]
    }
]