[
    {
        "fit": [
            21.814187499999996, 
            0.08668974488571926
        ]
    }, 
    {
        "fit": [
            21.659437499999996, 
            0.0868886777087175
        ]
    }, 
    {
        "fit": [
            21.149625, 
            0.0873484048615252
        ]
    }, 
    {
        "fit": [
            21.091874999999995, 
            0.088522235561655
        ]
    }, 
    {
        "fit": [
            20.5820625, 
            0.08898196271446271
        ]
    }, 
    {
        "fit": [
            20.043687499999997, 
            0.0900454226020252
        ]
    }, 
    {
        "fit": [
            19.863687499999997, 
            0.0923885521661301
        ]
    }, 
    {
        "fit": [
            19.589499999999997, 
            0.09355440395680559
        ]
    }, 
    {
        "fit": [
            19.296124999999996, 
            0.0940221100190676
        ]
    }, 
    {
        "fit": [
            19.051125, 
            0.09461786384436807
        ]
    }, 
    {
        "fit": [
            19.012874999999998, 
            0.09810923221955281
        ]
    }, 
    {
        "fit": [
            18.531437499999996, 
            0.10085798802487408
        ]
    }, 
    {
        "fit": [
            17.993062499999997, 
            0.1019214479124366
        ]
    }, 
    {
        "fit": [
            17.647187499999998, 
            0.10434697041243657
        ]
    }, 
    {
        "fit": [
            17.555437499999996, 
            0.10644152982187596
        ]
    }, 
    {
        "fit": [
            17.488374999999998, 
            0.10759430624568658
        ]
    }, 
    {
        "fit": [
            17.317375, 
            0.10937693011012597
        ]
    }, 
    {
        "fit": [
            17.302062499999998, 
            0.10960703510793851
        ]
    }, 
    {
        "fit": [
            16.7813125, 
            0.11244988265099906
        ]
    }, 
    {
        "fit": [
            16.6103125, 
            0.11423250651543845
        ]
    }, 
    {
        "fit": [
            16.4085, 
            0.11743711416918848
        ]
    }, 
    {
        "fit": [
            16.2496875, 
            0.12068445000243846
        ]
    }, 
    {
        "fit": [
            16.2421875, 
            0.12217362951543845
        ]
    }, 
    {
        "fit": [
            16.18725, 
            0.12411737705411047
        ]
    }, 
    {
        "fit": [
            16.040375, 
            0.12537823716918844
        ]
    }, 
    {
        "fit": [
            15.9854375, 
            0.12732198470786046
        ]
    }, 
    {
        "fit": [
            15.881562500000001, 
            0.12862557300243846
        ]
    }, 
    {
        "fit": [
            15.8665625, 
            0.13075988831724908
        ]
    }, 
    {
        "fit": [
            15.776125, 
            0.13201577187461044
        ]
    }, 
    {
        "fit": [
            15.70775, 
            0.1340072241504991
        ]
    }, 
    {
        "fit": [
            15.6173125, 
            0.13526310770786046
        ]
    }, 
    {
        "fit": [
            15.6023125, 
            0.13739742302267108
        ]
    }, 
    {
        "fit": [
            15.5750625, 
            0.14061707044567104
        ]
    }, 
    {
        "fit": [
            15.4435, 
            0.14064475885592106
        ]
    }, 
    {
        "fit": [
            15.41625, 
            0.14386440627892108
        ]
    }, 
    {
        "fit": [
            15.3928125, 
            0.14763778080666995
        ]
    }, 
    {
        "fit": [
            15.3778125, 
            0.1497720961214806
        ]
    }, 
    {
        "fit": [
            15.345, 
            0.15155291104549576
        ]
    }, 
    {
        "fit": [
            15.219, 
            0.15301943195473058
        ]
    }, 
    {
        "fit": [
            15.191749999999999, 
            0.15623907937773054
        ]
    }, 
    {
        "fit": [
            15.1205, 
            0.16392758414430528
        ]
    }, 
    {
        "fit": [
            15.09325, 
            0.16714723156730524
        ]
    }, 
    {
        "fit": [
            15.087875, 
            0.17700880979266312
        ]
    }, 
    {
        "fit": [
            15.047875, 
            0.17966346646843726
        ]
    }, 
    {
        "fit": [
            15.020624999999999, 
            0.18288311389143722
        ]
    }
]