[
    {
        "fit": [
            16.763357142857142, 
            0.11096750672854563
        ]
    }, 
    {
        "fit": [
            16.25107142857143, 
            0.1188421436650086
        ]
    }, 
    {
        "fit": [
            16.217642857142856, 
            0.11947515984364432
        ]
    }, 
    {
        "fit": [
            14.948500000000001, 
            0.12071010135180492
        ]
    }, 
    {
        "fit": [
            14.758928571428571, 
            0.12884047696474515
        ]
    }, 
    {
        "fit": [
            14.254142857142854, 
            0.1298263383820866
        ]
    }, 
    {
        "fit": [
            14.202571428571428, 
            0.13011708283441542
        ]
    }, 
    {
        "fit": [
            14.190571428571428, 
            0.13435716128018718
        ]
    }, 
    {
        "fit": [
            14.037142857142856, 
            0.1376194360662606
        ]
    }, 
    {
        "fit": [
            13.706142857142854, 
            0.13892939218044403
        ]
    }, 
    {
        "fit": [
            13.306071428571428, 
            0.14702355316403587
        ]
    }, 
    {
        "fit": [
            13.303785714285713, 
            0.16709583652004886
        ]
    }
]