[
    {
        "fit": [
            24.249785714285714, 
            0.11168111004331328
        ]
    }, 
    {
        "fit": [
            23.76557142857143, 
            0.11768783544705078
        ]
    }, 
    {
        "fit": [
            21.482357142857143, 
            0.1189703929921434
        ]
    }, 
    {
        "fit": [
            16.467928571428576, 
            0.12654728413278796
        ]
    }, 
    {
        "fit": [
            15.66335714285714, 
            0.14845828016449344
        ]
    }, 
    {
        "fit": [
            15.01464285714286, 
            0.1493349523665223
        ]
    }, 
    {
        "fit": [
            12.960214285714285, 
            0.1604521139854746
        ]
    }, 
    {
        "fit": [
            12.806571428571429, 
            0.1735546915954422
        ]
    }, 
    {
        "fit": [
            12.724285714285717, 
            0.205577925123641
        ]
    }, 
    {
        "fit": [
            11.841571428571429, 
            0.20600946889353727
        ]
    }, 
    {
        "fit": [
            11.563214285714286, 
            0.20813277691422297
        ]
    }, 
    {
        "fit": [
            11.401285714285711, 
            0.2667425638565068
        ]
    }, 
    {
        "fit": [
            11.2705, 
            0.3031327721083481
        ]
    }
]