[
    {
        "fit": [
            18.66207142857143, 
            0.11777427761296057
        ]
    }, 
    {
        "fit": [
            16.87057142857143, 
            0.12264485834900464
        ]
    }, 
    {
        "fit": [
            16.093071428571427, 
            0.13031370111929205
        ]
    }, 
    {
        "fit": [
            16.077857142857145, 
            0.13284122330137688
        ]
    }, 
    {
        "fit": [
            15.65157142857143, 
            0.13342911647816869
        ]
    }, 
    {
        "fit": [
            13.305357142857144, 
            0.1448613596789057
        ]
    }, 
    {
        "fit": [
            12.714571428571432, 
            0.15049722397477153
        ]
    }, 
    {
        "fit": [
            12.582857142857145, 
            0.18449283390540355
        ]
    }, 
    {
        "fit": [
            12.273214285714287, 
            0.1878489729922
        ]
    }
]